{
	"meals": [
		{
			"title": "Pierogies",
			"description": "Tasty pierogies",
			"directions": "Cook the pierogies in a pot.",
			"ingredients": [
				{
					"ingredient": "Pierogies"
				},
				{
					"ingredient": "Sour cream"
				},
				{
					"ingredient": "Cheese"
				},
				{
					"ingredient": "Butter"
				},
				{
					"ingredient": "Salt"
				},
				{
					"ingredient": "Bacon bits"
				},
				{
					"ingredient": "Onions"
				},
				{
					"ingredient": "Chives"
				}
			],
			"type": "Main"
		},
		{
			"title": "Burger",
			"description": "A tasty burger.",
      "directions": "Grill the burger on the barbecue.",
			"ingredients": [
				{
					"ingredient": "Burger patty"
				},
				{
					"ingredient": "Burger bun"
				},
				{
					"ingredient": "Cheese slice"
				},
				{
					"ingredient": "Ketchup"
				},
				{
					"ingredient": "Mustard"
				},
				{
					"ingredient": "Frank's"
				},
				{
					"ingredient": "Seasoning"
				},
				{
					"ingredient": "Bacon"
				},
				{
					"ingredient": "Pickles"
				},
				{
					"ingredient": "Tomato"
				},
				{
					"ingredient": "Letuce"
				},
				{
					"ingredient": "Onions"
				}
			],
			"type": "Main"
		},
		{
			"title": "Hot Dogs / Smokies",
			"description": "Some tasty hot dogs or smokies.",
      "directions": "Grill the hot dogs/smokies on the barbecue.",
			"ingredients": [
				{
					"ingredient": "Hot dogs (or smokies)"
				},
				{
					"ingredient": "Hot dog buns"
				},
				{
					"ingredient": "Ketchup"
				},
				{
					"ingredient": "Mustard"
				},
				{
					"ingredient": "Cheese"
				},
				{
					"ingredient": "Chips"
				}
			],
			"type": "Main"
		},
		{
			"title": "Scrambled Eggs",
			"description": "Some very nice scrambled eggs.",
      "directions": "Scramble the eggs in a pan.",
			"ingredients": [
				{
					"ingredient": "Eggs"
				},
				{
					"ingredient": "Milk"
				},
				{
					"ingredient": "Sharp cheddar"
				}
			],
			"type": "Side"
		},
		{
			"type": "Main",
			"title": "Sausages",
			"description": "Some tasty sausages.",
      "directions": "Grill the sausages on the barbecue.",
			"ingredients": [
				{
					"ingredient": "Sausages"
				},
				{
					"ingredient": "Mustard (dijon)"
				}
			]
		},
		{
			"type": "Side",
			"title": "Caesar Salad",
			"description": "A very good caesar salad",
      "directions": "Mix the lettuce with the dressing.",
			"ingredients": [
				{
					"ingredient": "Romain lettuce"
				},
				{
					"ingredient": "Caesar salad dressing"
				}
			]
		}
	]
}
